MANIFEST.in
README.md
requirements.txt
setup.py
libpunchq/__init__.py
libpunchq/cli.py
libpunchq/conversion.py
libpunchq/exceptions.py
libpunchq/mqstate.py
libpunchq/utils.py
libpunchq/wordlists/mq_channels.txt
libpunchq/wordlists/mq_users.txt
punch_q.egg-info/PKG-INFO
punch_q.egg-info/SOURCES.txt
punch_q.egg-info/dependency_links.txt
punch_q.egg-info/entry_points.txt
punch_q.egg-info/requires.txt
punch_q.egg-info/top_level.txt