Metadata-Version: 1.2
Name: punch-q
Version: 1.2.0
Summary: A small utility to play with IBM Websphere MQ
Home-page: https://github.com/sensepost/punch-q
Author: Leon Jacobs
Author-email: leon@sensepost.com
License: GPL-3
Download-URL: https://github.com/sensepost/punch-q/archive/1.2.0.tar.gz
Keywords: ibm,websphere,mq,security
Platform: UNKNOWN
Classifier: Operating System :: OS Independent
Classifier: Natural Language :: English
Classifier: Programming Language :: Python :: 2
Classifier: Programming Language :: Python :: 3
Requires-Python: >=2.7
